distnet2d-0.2.4.dist-info/licenses/LICENSE.txt
distnet_2d/__init__.py
distnet_2d/data/__init__.py
distnet_2d/data/center_edm.py
distnet_2d/data/dydx_iterator.py
distnet_2d/data/medoid.py
distnet_2d/data/swim1d.py
distnet_2d/model/__init__.py
distnet_2d/model/architectures.py
distnet_2d/model/distnet_2d.py
distnet_2d/model/distnet_2d_seg.py
distnet_2d/model/gradient_accumulator.py
distnet_2d/model/layers.py
distnet_2d/model/spatial_attention.py
distnet_2d/utils/__init__.py
distnet_2d/utils/agc.py
distnet_2d/utils/helpers.py
distnet_2d/utils/image_derivatives_np.py
distnet_2d/utils/image_derivatives_tf.py
distnet_2d/utils/losses.py
distnet_2d/utils/lovasz_loss.py
distnet_2d/utils/metrics_tf.py
distnet_2d/utils/objectwise_computation_tf.py
distnet2d-0.2.4.dist-info/METADATA
distnet2d-0.2.4.dist-info/WHEEL
distnet2d-0.2.4.dist-info/top_level.txt
distnet2d-0.2.4.dist-info/RECORD
