Metadata-Version: 2.4
Name: DiSTNet2D
Version: 0.2.4
Summary: tensorflow/keras implementation of DiSTNet 2D
Home-page: https://github.com/jeanollion/distnet2d
Download-URL: https://github.com/jeanollion/distnet2d/releases/download/v0.2.4/distnet2d-0.2.4.tar.gz
Author: Jean Ollion
Author-email: jean.ollion@sabilab.fr
Keywords: Segmentation,Tracking,Cell,Tensorflow,Keras
Classifier: Development Status :: 4 - Beta
Classifier: Intended Audience :: Science/Research
Classifier: Topic :: Scientific/Engineering :: Artificial Intelligence
Classifier: Topic :: Scientific/Engineering :: Image Processing
Classifier: License :: OSI Approved :: GNU General Public License v3 or later (GPLv3+)
Classifier: Programming Language :: Python :: 3
Requires-Python: >=3
License-File: LICENSE.txt
Requires-Dist: numpy
Requires-Dist: scipy
Requires-Dist: tensorflow>=2.7.1
Requires-Dist: edt>=2.0.2
Requires-Dist: scikit-fmm
Requires-Dist: numba
Requires-Dist: dataset_iterator>=0.5.7
Requires-Dist: elasticdeform>=0.4.7
Dynamic: author
Dynamic: author-email
Dynamic: classifier
Dynamic: description
Dynamic: description-content-type
Dynamic: download-url
Dynamic: home-page
Dynamic: keywords
Dynamic: license-file
Dynamic: requires-dist
Dynamic: requires-python
Dynamic: summary
